telnetsrvlib
