Metadata-Version: 1.0
Name: telnetsrvlib
Version: 1.0.2
Summary: Telnet server and CLI
Home-page: https://sourceforge.net/projects/pytelnetsrvlib/
Author: Adrian Hungate
Author-email: adrian@tlspu.com
License: LGPG
Platform: UNKNOWN
